odoo/addons/energy_selfconsumption_cooperator/__init__.py
odoo/addons/energy_selfconsumption_cooperator/__manifest__.py
odoo/addons/energy_selfconsumption_cooperator/i18n/ca_ES.po
odoo/addons/energy_selfconsumption_cooperator/i18n/energy_selfconsumption_cooperator.pot
odoo/addons/energy_selfconsumption_cooperator/i18n/es.po
odoo/addons/energy_selfconsumption_cooperator/i18n/eu_ES.po
odoo/addons/energy_selfconsumption_cooperator/models/__init__.py
odoo/addons/energy_selfconsumption_cooperator/models/supply_point.py
odoo/addons/energy_selfconsumption_cooperator/static/description/icon.png
odoo/addons/energy_selfconsumption_cooperator/views/res_partner_views.xml
odoo/addons/energy_selfconsumption_cooperator/views/supply_point_views.xml
odoo14_addon_energy_selfconsumption_cooperator-14.0.1.3.0.dist-info/METADATA
odoo14_addon_energy_selfconsumption_cooperator-14.0.1.3.0.dist-info/WHEEL
odoo14_addon_energy_selfconsumption_cooperator-14.0.1.3.0.dist-info/top_level.txt
odoo14_addon_energy_selfconsumption_cooperator-14.0.1.3.0.dist-info/RECORD
