Metadata-Version: 2.1
Name: odoo14-addon-energy-selfconsumption-cooperator
Version: 14.0.1.3.0
Summary: Module glue between Energy Self-consumption and Cooperator
Home-page: https://coopdevs.org
Author: Coopdevs Treball SCCL & Som Energia SCCL
License: UNKNOWN
Platform: UNKNOWN
Classifier: Programming Language :: Python
Classifier: Framework :: Odoo
Classifier: Framework :: Odoo :: 14.0
Requires-Python: >=3.6
Requires-Dist: odoo14-addon-cooperator
Requires-Dist: odoo14-addon-energy-selfconsumption (==14.0.2.1.0)
Requires-Dist: odoo (<14.1dev,>=14.0a)
